qpso/__init__.py
qpso/qpso.py
qpso-0.0.1.dist-info/LICENSE
qpso-0.0.1.dist-info/METADATA
qpso-0.0.1.dist-info/WHEEL
qpso-0.0.1.dist-info/top_level.txt
qpso-0.0.1.dist-info/RECORD
