Metadata-Version: 2.1
Name: qpso
Version: 0.0.1
Summary: A Python implementation of quantum particle swarm optimization (QPSO).
Home-page: https://github.com/ngroup/qpso
Author: Chun Nien
Author-email: contact@chunnien.com
License: UNKNOWN
Keywords: optimization qpso swarm
Platform: UNKNOWN
Classifier: Development Status :: 3 - Alpha
Classifier: Intended Audience :: Developers
Classifier: License :: OSI Approved :: MIT License
Classifier: Programming Language :: Python :: 3.6
Classifier: Programming Language :: Python :: 3.7
Requires-Dist: numpy
